typst/__init__.py
typst/__init__.pyi
typst/_typst.cpython-314t-darwin.so
typst/py.typed
typst-0.14.7.dist-info/METADATA
typst-0.14.7.dist-info/WHEEL
typst-0.14.7.dist-info/licenses/LICENSE
typst-0.14.7.dist-info/RECORD
