Metadata-Version: 2.4
Name: typst
Version: 0.14.7
Classifier: Programming Language :: Rust
Classifier: Programming Language :: Python :: Implementation :: CPython
Classifier: Programming Language :: Python :: Implementation :: PyPy
License-File: LICENSE
License-Expression: Apache-2.0
Requires-Python: >=3.8
Project-URL: Documentation, https://github.com/messense/typst-py/blob/main/README.md
Project-URL: Homepage, https://github.com/messense/typst-py/
Project-URL: Readme, https://github.com/messense/typst-py/blob/main/README.md
Project-URL: Repository, https://github.com/messense/typst-py
